nonebot_plugin_okashi/__init__.py
nonebot_plugin_okashi-0.1.6.dist-info/licenses/LICENSE
nonebot_plugin_okashi-0.1.6.dist-info/METADATA
nonebot_plugin_okashi-0.1.6.dist-info/WHEEL
nonebot_plugin_okashi-0.1.6.dist-info/top_level.txt
nonebot_plugin_okashi-0.1.6.dist-info/RECORD
