Metadata-Version: 2.4
Name: nonebot-plugin-okashi
Version: 0.1.6
Summary: KIRAKIRA账号审核入群功能
Author-email: Yasaitori <caijidayo@outlook.com>
License: AGPL-3.0
Project-URL: Homepage, https://github.com/YasaitoriOvO/nonebot-plugin-okashi
Project-URL: Repository, https://github.com/YasaitoriOvO/nonebot-plugin-okashi
Classifier: Programming Language :: Python :: 3.8
Classifier: License :: OSI Approved :: GNU Affero General Public License v3
Classifier: Operating System :: OS Independent
Requires-Python: >=3.8
License-File: LICENSE
Requires-Dist: httpx>=0.23.3
Requires-Dist: nonebot2>=2.0.0rc3
Requires-Dist: nonebot-adapter-onebot>=2.0.0b1
Dynamic: license-file
